Workbook
Name Taper_rate: '[1]DCF Model'!$B$22
Name Taper_rate: 'DCF Model'!$C$23
Name Tax_rate: 'DCF Model'!$C$27
Name Tpaer_rate: 'DCF Model'!$C$23
Name UPDATE: '[1]Historical Data'!#REF!
Name UPDATE: 'Data Sheet'!$E$1
Name UPDATE: #REF!

Sheet DCF Model
B1: DISCOUNTED CASH FLOW MODEL
B3: HUL DCF MODEL
B5: Company Overview
B7: Hindustan Unilever Limited is a consumer goods arm of Unilever, operating multiple product divisions including:
B9: Home Care - Fabric cleaning and household care (Surf Excel, Rin, Vim)
B10: Beauty & Wellbeing - Premium hair care, skin care, and health (Dove, Sunsilk, Vaseline)
B11: Personal Care - Mass skin cleansing and oral care (Lux, Lifebuoy, Glow & Lovely)
B12: Foods & Refreshment - Tea, coffee, nutrition, and culinary brands (Horlicks, Brooke Bond, Kissan)
B14: Total Retail Reach: 9+ million retail outlets across India | Household Penetration: ~90% of Indian homes
B17: Key Assumptions & Methodology
B19: Parameter | C19: Value | D19: Rationale
B20: Valuation Date
B21: Projection Period
B22: Revenue Growth% | C22: 0.07 | D22: Based on management guidance
B23: Annual Growth Tapering | C23: 0.01
B24: Terminal Growth Rate | C24: 0.045 | D24: Conservative long term growth consdering India's GDP
B25: Risk-Free Rate (Rf) | C25: 0.07 | D25: 10 year gov bond yield
B26: Equity Risk Premium (ERP) | C26: =13%-C25 -> 0.06 | D26: Expected return over risk free rate for Equity Investors
B27: Tax Rate | C27: 0.25 | D27: Effective
B29: Financial Performance (₹ Crores)
B31: INCOME STATEMENT
B33: Particulars | C33: ='Data Sheet'!G16 -> 44651 | D33: ='Data Sheet'!H16 -> 45016 | E33: ='Data Sheet'!I16 -> 45382 | F33: ='Data Sheet'!J16 -> 45747 | G33: ='Data Sheet'!K16 -> 46112 | H33: CAGR
B34: Sales | C34: ='Data Sheet'!G17 -> 52446 | D34: ='Data Sheet'!H17 -> 60580 | E34: ='Data Sheet'!I17 -> 61896 | F34: ='Data Sheet'!J17 -> 61328 | G34: ='Data Sheet'!K17 -> 64468
B35: % growth | D35: =D34/C34-1 -> 0.15509286 | E35: =E34/D34-1 -> 0.021723341 | F35: =F34/E34-1 -> -0.0091766835 | G35: =G34/F34-1 -> 0.051200104 | H35: =_xlfn.RRI(4,C34,G34) -> 0.052950504
B37: Cost of Goods Sold | C37: =SUM('Data Sheet'!G18,-'Data Sheet'!G19,'Data Sheet'!G20:G21) -> 26521 | D37: =SUM('Data Sheet'!H18,-'Data Sheet'!H19,'Data Sheet'!H20:H21) -> 32527 | E37: =SUM('Data Sheet'!I18,-'Data Sheet'!I19,'Data Sheet'!I20:I21) -> 30642 | F37: =SUM('Data Sheet'!J18,-'Data Sheet'!J19,'Data Sheet'!J20:J21) -> 30567 | G37: =SUM('Data Sheet'!K18,-'Data Sheet'!K19,'Data Sheet'!K20:K21) -> 32459
B38: % of revenue | C38: =C37/C34 -> 0.50568203 | D38: =D37/D34 -> 0.53692638 | E38: =E37/E34 -> 0.49505622 | F38: =F37/F34 -> 0.49841834 | G38: =G37/G34 -> 0.5034901
B40: Gross Profit | C40: =C34-C37 -> 25925 | D40: =D34-D37 -> 28053 | E40: =E34-E37 -> 31254 | F40: =F34-F37 -> 30761 | G40: =G34-G37 -> 32009
B41: % margin | C41: =C40/C34 -> 0.49431797 | D41: =D40/D34 -> 0.46307362 | E41: =E40/E34 -> 0.50494378 | F41: =F40/F34 -> 0.50158166 | G41: =G40/G34 -> 0.4965099
B43: Operating Expenses | C43: =SUM('Data Sheet'!G22:G24) -> 13068 | D43: =SUM('Data Sheet'!H22:H24) -> 13906 | E43: =SUM('Data Sheet'!I22:I24) -> 16595 | F43: =SUM('Data Sheet'!J22:J24) -> 16063 | G43: =SUM('Data Sheet'!K22:K24) -> 16970
B44: % of revenue | C44: =C43/C34 -> 0.24917058 | D44: =D43/D34 -> 0.22954771 | E44: =E43/E34 -> 0.26811102 | F44: =F43/F34 -> 0.26191951 | G44: =G43/G34 -> 0.26323137
B46: EBITDA | C46: =C40-C43 -> 12857 | D46: =D40-D43 -> 14147 | E46: =E40-E43 -> 14659 | F46: =F40-F43 -> 14698 | G46: =G40-G43 -> 15039
B47: % margin | C47: =C46/C34 -> 0.24514739 | D47: =D46/D34 -> 0.23352592 | E47: =E46/E34 -> 0.23683275 | F47: =F46/F34 -> 0.23966214 | G47: =G46/G34 -> 0.23327853
B49: Depreciation | C49: ='Data Sheet'!G26 -> 1091 | D49: ='Data Sheet'!H26 -> 1137 | E49: ='Data Sheet'!I26 -> 1216 | F49: ='Data Sheet'!J26 -> 1253 | G49: ='Data Sheet'!K26 -> 1333
B50: % of net block | C50: =C49/C34 -> 0.020802349 | D50: =D49/D34 -> 0.01876857 | E50: =E49/E34 -> 0.019645858 | F50: =F49/F34 -> 0.020431124 | G50: =G49/G34 -> 0.020676925
B52: EBIT | C52: =C46-C49 -> 11766 | D52: =D46-D49 -> 13010 | E52: =E46-E49 -> 13443 | F52: =F46-F49 -> 13445 | G52: =G46-G49 -> 13706
B53: % margin | C53: =C52/C34 -> 0.22434504 | D53: =D52/D34 -> 0.21475735 | E53: =E52/E34 -> 0.21718689 | F53: =F52/F34 -> 0.21923102 | G53: =G52/G34 -> 0.2126016
B55: Other Income | C55: ='Data Sheet'!G25 -> 219 | D55: ='Data Sheet'!H25 -> 448 | E55: ='Data Sheet'!I25 -> 817 | F55: ='Data Sheet'!J25 -> 1355 | G55: ='Data Sheet'!K25 -> 4923
B57: Interest | C57: ='Data Sheet'!G27 -> 106 | D57: ='Data Sheet'!H27 -> 114 | E57: ='Data Sheet'!I27 -> 334 | F57: ='Data Sheet'!J27 -> 381 | G57: ='Data Sheet'!K27 -> 410
B58: % of debt | C58: =C57/'Data Sheet'!G59 -> 0.10162991 | D58: =D57/'Data Sheet'!H59 -> 0.093519278 | E58: =E57/'Data Sheet'!I59 -> 0.22506739 | F58: =F57/'Data Sheet'!J59 -> 0.23118932 | G58: =G57/'Data Sheet'!K59 -> 0.27740189
B60: Profit before tax | C60: =C52+C55-C57 -> 11879 | D60: =D52+D55-D57 -> 13344 | E60: =E52+E55-E57 -> 13926 | F60: =F52+F55-F57 -> 14419 | G60: =G52+G55-G57 -> 18219
B61: % of revenue | C61: =C60/C34 -> 0.22649964 | D61: =D60/D34 -> 0.22027072 | E61: =E60/E34 -> 0.22499031 | F61: =F60/F34 -> 0.23511284 | G61: =G60/G34 -> 0.28260532
B63: Tax | C63: ='Data Sheet'!G29 -> 2987 | D63: ='Data Sheet'!H29 -> 3201 | E63: ='Data Sheet'!I29 -> 3644 | F63: ='Data Sheet'!J29 -> 3748 | G63: ='Data Sheet'!K29 -> 3160
B64: % of PBT | C64: =C63/C60 -> 0.25145214 | D64: =D63/D60 -> 0.23988309 | E64: =E63/E60 -> 0.26166882 | F64: =F63/F60 -> 0.25993481 | G64: =G63/G60 -> 0.1734453
B66: Net profit | C66: =C60-C63 -> 8892 | D66: =D60-D63 -> 10143 | E66: =E60-E63 -> 10282 | F66: =F60-F63 -> 10671 | G66: =G60-G63 -> 15059
B67: % of revenue | C67: =C66/C34 -> 0.16954582 | D67: =D66/D34 -> 0.1674315 | E67: =E66/E34 -> 0.16611736 | F67: =F66/F34 -> 0.17399883 | G67: =G66/G34 -> 0.23358876
B69: BALANCE SHEET
B71: Particulars | C71: ='Data Sheet'!G56 -> 44651 | D71: ='Data Sheet'!H56 -> 45016 | E71: ='Data Sheet'!I56 -> 45382 | F71: ='Data Sheet'!J56 -> 45747 | G71: ='Data Sheet'!K56 -> 46112
B72: Equity Share Capital | C72: ='Data Sheet'!G57 -> 235 | D72: ='Data Sheet'!H57 -> 235 | E72: ='Data Sheet'!I57 -> 235 | F72: ='Data Sheet'!J57 -> 235 | G72: ='Data Sheet'!K57 -> 235
B73: Reserves | C73: ='Data Sheet'!G58 -> 48826 | D73: ='Data Sheet'!H58 -> 50069 | E73: ='Data Sheet'!I58 -> 50983 | F73: ='Data Sheet'!J58 -> 49167 | G73: ='Data Sheet'!K58 -> 48504
B74: Borrowings | C74: ='Data Sheet'!G59 -> 1043 | D74: ='Data Sheet'!H59 -> 1219 | E74: ='Data Sheet'!I59 -> 1484 | F74: ='Data Sheet'!J59 -> 1648 | G74: ='Data Sheet'!K59 -> 1478
B75: Other Liabilities | C75: ='Data Sheet'!G60 -> 20402 | D75: ='Data Sheet'!H60 -> 21554 | E75: ='Data Sheet'!I60 -> 25787 | F75: ='Data Sheet'!J60 -> 28813 | G75: ='Data Sheet'!K60 -> 29521
B76: Total | C76: =SUM(C72:C75) -> 70506 | D76: =SUM(D72:D75) -> 73077 | E76: =SUM(E72:E75) -> 78489 | F76: =SUM(F72:F75) -> 79863 | G76: =SUM(G72:G75) -> 79738
B77: Net Block | C77: ='Data Sheet'!G62 -> 51473 | D77: ='Data Sheet'!H62 -> 52678 | E77: ='Data Sheet'!I62 -> 53744 | F77: ='Data Sheet'!J62 -> 54335 | G77: ='Data Sheet'!K62 -> 57428
B78: Capital Work in Progress | C78: ='Data Sheet'!G63 -> 1313 | D78: ='Data Sheet'!H63 -> 1132 | E78: ='Data Sheet'!I63 -> 1025 | F78: ='Data Sheet'!J63 -> 1009 | G78: ='Data Sheet'!K63 -> 880
B79: Investments | C79: ='Data Sheet'!G64 -> 3521 | D79: ='Data Sheet'!H64 -> 2882 | E79: ='Data Sheet'!I64 -> 4625 | F79: ='Data Sheet'!J64 -> 3810 | G79: ='Data Sheet'!K64 -> 4359
B80: Receivables | C80: ='Data Sheet'!G67 -> 2236 | D80: ='Data Sheet'!H67 -> 3079 | E80: ='Data Sheet'!I67 -> 2997 | F80: ='Data Sheet'!J67 -> 3819 | G80: ='Data Sheet'!K67 -> 3379
B81: Inventory | C81: ='Data Sheet'!G68 -> 4096 | D81: ='Data Sheet'!H68 -> 4251 | E81: ='Data Sheet'!I68 -> 4022 | F81: ='Data Sheet'!J68 -> 4415 | G81: ='Data Sheet'!K68 -> 4789
B82: Cash & Bank | C82: ='Data Sheet'!G69 -> 3846 | D82: ='Data Sheet'!H69 -> 4678 | E82: ='Data Sheet'!I69 -> 7559 | F82: ='Data Sheet'!J69 -> 7554 | G82: ='Data Sheet'!K69 -> 3248
B83: Other Assets | C83: ='Data Sheet'!G65-SUM('Data Sheet'!G67:G69) -> 4021 | D83: ='Data Sheet'!H65-SUM('Data Sheet'!H67:H69) -> 4377 | E83: ='Data Sheet'!I65-SUM('Data Sheet'!I67:I69) -> 4517 | F83: ='Data Sheet'!J65-SUM('Data Sheet'!J67:J69) -> 4921 | G83: ='Data Sheet'!K65-SUM('Data Sheet'!K67:K69) -> 5655
B84: Total | C84: =SUM(C77:C83) -> 70506 | D84: =SUM(D77:D83) -> 73077 | E84: =SUM(E77:E83) -> 78489 | F84: =SUM(F77:F83) -> 79863 | G84: =SUM(G77:G83) -> 79738
B86: Revenue Projections & Growth Assumptions
B88: Year | C88: FY27E | D88: FY28E | E88: FY29E | F88: FY30E | G88: FY31E
B89: Revenue Growth % | C89: {=CHOOSE(D91,C92:G92,C93:G93,C94:G94)} -> 0.07 | D89: 0.06 | E89: 0.05 | F89: 0.04 | G89: 0.03
B90: Revenue (in Crs.) | C90: =G34*(1+C89) -> 68980.76 | D90: =C90*(1+D89) -> 73119.606 | E90: =D90*(1+E89) -> 76775.586 | F90: =E90*(1+F89) -> 79846.609 | G90: =F90*(1+G89) -> 82242.008
B91: Chosen Scenario: | C91: Base Case | D91: =MATCH(C91,B92:B94,0) -> 1
B92: Base Case | C92: =C22 -> 0.07 | D92: =C92-Taper_rate -> 0.06 | E92: =D92-Taper_rate -> 0.05 | F92: =E92-Taper_rate -> 0.04 | G92: =F92-Taper_rate -> 0.03
B93: Best Case | C93: =C92+4% -> 0.11 | D93: =C93-Taper_rate -> 0.1 | E93: =D93-Taper_rate -> 0.09 | F93: =E93-Taper_rate -> 0.08 | G93: =F93-Taper_rate -> 0.07
B94: Worst Case | C94: =C92-4% -> 0.03 | D94: =C94-Taper_rate -> 0.02 | E94: =D94-Taper_rate -> 0.01 | F94: =E94-Taper_rate -> 0 | G94: =F94-Taper_rate -> -0.01
B96: Free Cash Flow Projections (₹ Crores)
B98: Particulars | C98: =C88 -> FY27E | D98: =D88 -> FY28E | E98: =E88 -> FY29E | F98: =F88 -> FY30E | G98: =G88 -> FY31E
B99: Revenue | C99: =C90 -> 68980.76 | D99: =D90 -> 73119.606 | E99: =E90 -> 76775.586 | F99: =F90 -> 79846.609 | G99: =G90 -> 82242.008
B100: EBITDA Margin % | C100: =G47 -> 0.23327853 | D100: =C100 -> 0.23327853 | E100: =D100 -> 0.23327853 | F100: =E100 -> 0.23327853 | G100: =F100 -> 0.23327853
B101: EBITDA | C101: =C99*C100 -> 16091.73 | D101: =D99*D100 -> 17057.234 | E101: =E99*E100 -> 17910.095 | F101: =F99*F100 -> 18626.499 | G101: =G99*G100 -> 19185.294
B102: Less: Depreciation | C102: =C99*2% -> 1379.6152 | D102: =D99*2% -> 1462.3921 | E102: =E99*2% -> 1535.5117 | F102: =F99*2% -> 1596.9322 | G102: =G99*2% -> 1644.8402
B103: EBIT | C103: =C101-C102 -> 14712.115 | D103: =D101-D102 -> 15594.842 | E103: =E101-E102 -> 16374.584 | F103: =F101-F102 -> 17029.567 | G103: =G101-G102 -> 17540.454
B104: Less: Tax | C104: =C103*Tax_rate -> 3678.0287 | D104: =D103*Tax_rate -> 3898.7104 | E104: =E103*Tax_rate -> 4093.6459 | F104: =F103*Tax_rate -> 4257.3918 | G104: =G103*Tax_rate -> 4385.1135
B105: NOPAT | C105: =C103-C104 -> 11034.086 | D105: =D103-D104 -> 11696.131 | E105: =E103-E104 -> 12280.938 | F105: =F103-F104 -> 12772.175 | G105: =G103-G104 -> 13155.341
B106: Add: Depreciation | C106: =C102 -> 1379.6152 | D106: =D102 -> 1462.3921 | E106: =E102 -> 1535.5117 | F106: =F102 -> 1596.9322 | G106: =G102 -> 1644.8402
B107: Less: Reinvestment | C107: =C105*23% -> 2537.8398 | D107: =D105*23% -> 2690.1102 | E107: =E105*23% -> 2824.6157 | F107: =F105*23% -> 2937.6003 | G107: =G105*23% -> 3025.7283
B108: Free Cash Flow to Firm | C108: =C105+C106-C107 -> 9875.8615 | D108: =D105+D106-D107 -> 10468.413 | E108: =E105+E106-E107 -> 10991.834 | F108: =F105+F106-F107 -> 11431.507 | G108: =G105+G106-G107 -> 11774.452
B110: WACC Calculation
B112: Target Capital Structure
B113: Proportion of Debt | C113: ='COMPS '!F20 -> 0.0088417755
B114: Proportion of Equity | C114: =1-C113 -> 0.99115822
B115: Current Capital Structure
B116: Market Cap | C116: ='COMPS '!D6 -> 500498.14
B117: Total Debt | C117: ='COMPS '!E6 -> 1478
B118: Debt / Equity | C118: =C117/C116 -> 0.0029530579
B119: Cost of Debt
B120: Pre-Tax Cost of Debt | C120: 0.075
B121: Tax Rate | C121: =Tax_rate -> 0.25
B122: After-Tax Cost of Debt | C122: =C120*(1-C121) -> 0.05625
B123: Cost of Equity
B124: Risk Free Rate | C124: =C25 -> 0.07
B125: Equity Risk Premium | C125: =C26 -> 0.06
B126: Levered Equity Beta | C126: ='COMPS '!L6 -> 0.45
B127: Cost of Equity | C127: =C124+C126*C125 -> 0.097
B128: WACC | C128: =(C127*C114)+(C113*C122) -> 0.096639698
B130: Terminal Value Calculation
B132: Terminal Year FCF (FY31) | C132: =G108 -> 11774.452
...

Sheet COMPS 
B3: COMPS DATA
B5: Name | C5: Price | D5: Mar Cap . | E5: Debt Rs.Cr. | F5: Debt / Eq | G5: Sales Rs.Cr. | H5: EV / EBITDA | I5: Net Income | J5: Cash Rs.Cr. | K5: EBITDA | L5: Beta
B6: Hind. Unilever | C6: 2130.15 | D6: 500498.14 | E6: 1478 | F6: 0.03 | G6: 64468 | H6: 31.59 | I6: 15059 | J6: 3248 | K6: 15039 | L6: 0.45
B7: ITC | C7: 288 | D7: 360848.72 | E7: 2399.06 | F7: 0.03 | G7: 78868.4 | H7: 11.96 | I7: 21018.15 | J7: 3008.79 | K7: 27306 | L7: 0.65
B8: Nestle India | C8: 1417 | D8: 273242.19 | E8: 444.16 | F8: 0.08 | G8: 23154.6 | H8: 50.98 | I8: 3544.6 | J8: 1340.87 | K8: 5306.96 | L8: 0.42
B9: Varun Beverages | C9: 504.05 | D9: 170484.65 | E9: 2508.18 | F9: 0.13 | G9: 22692.63 | H9: 30.14 | I9: 3209.4 | J9: 1998.49 | K9: 5304.92 | L9: 0.85
B10: Britannia Inds. | C10: 5115 | D10: 123204.09 | E10: 1380.28 | F10: 0.27 | G10: 19151.59 | H10: 33.23 | I10: 2537.01 | J10: 352.44 | K10: 3514.34 | L10: 0.55
B12: INDUSTRY DATA
B14: Name | C14: Equity Value | D14: Total Debt | E14: Debt/Equity | F14: Debt/Capital | G14: Tax Rate% | H14: Levered Beta | I14: Unlevered Beta
B15: ITC | C15: =D7 -> 360848.72 | D15: =E7 -> 2399.06 | E15: =D15/C15 -> 0.0066483816 | F15: =D15/(C15+D15) -> 0.0066044726 | G15: =Tax_rate -> 0.25 | H15: =L7 -> 0.65 | I15: =H15/(1+E15*(1-G15)) -> 0.64677499
B16: Nestle India | C16: =D8 -> 273242.19 | D16: =E8 -> 444.16 | E16: =D16/C16 -> 0.0016255176 | F16: =D16/(C16+D16) -> 0.0016228796 | G16: =Tax_rate -> 0.25 | H16: =L8 -> 0.42 | I16: =H16/(1+E16*(1-G16)) -> 0.41948859
B17: Varun Beverages | C17: =D9 -> 170484.65 | D17: =E9 -> 2508.18 | E17: =D17/C17 -> 0.014712058 | F17: =D17/(C17+D17) -> 0.014498751 | G17: =Tax_rate -> 0.25 | H17: =L9 -> 0.85 | I17: =H17/(1+E17*(1-G17)) -> 0.84072342
B18: Britannia Inds. | C18: =D10 -> 123204.09 | D18: =E10 -> 1380.28 | E18: =D18/C18 -> 0.0112032 | F18: =D18/(C18+D18) -> 0.011079078 | G18: =Tax_rate -> 0.25 | H18: =L10 -> 0.55 | I18: =H18/(1+E18*(1-G18)) -> 0.54541719
B19: Average | E19: =AVERAGE(E15:E18) -> 0.0085472891 | F19: =AVERAGE(F15:F18) -> 0.0084512954 | G19: =AVERAGE(G15:G18) -> 0.25 | H19: =AVERAGE(H15:H18) -> 0.6175 | I19: =AVERAGE(I15:I18) -> 0.61310105
B20: Median | E20: =MEDIAN(E15:E18) -> 0.0089257906 | F20: =MEDIAN(F15:F18) -> 0.0088417755 | G20: =MEDIAN(G15:G18) -> 0.25 | H20: =MEDIAN(H15:H18) -> 0.6 | I20: =MEDIAN(I15:I18) -> 0.59609609
B23: COMPARABLE COMPANIES ANALYSIS
J25: Financial Data | M25: Valuation
B26: Name | C26: Price | D26: Shares | E26: Market Cap | F26: Debt | G26: Cash Eqv | H26: EV | I26: Sales | J26: EBITDA | K26: Earnings | L26: EV/Sales | M26: EV/EBITDA | N26: P/E
B27: ITC | C27: =C7 -> 288 | D27: =E27/C27 -> 1252.9469 | E27: =D7 -> 360848.72 | F27: =E6 -> 1478 | G27: =J7 -> 3008.79 | H27: =E27+F27 -> 362326.72 | I27: =G7 -> 78868.4 | J27: =K7 -> 27306 | K27: =I7 -> 21018.15 | L27: =H27/I27 -> 4.5940671 | M27: =H27/J27 -> 13.269125 | N27: =E27/K27 -> 17.168434
B28: Nestle India | C28: =C8 -> 1417 | D28: =E28/C28 -> 192.83147 | E28: =D8 -> 273242.19 | F28: =E7 -> 2399.06 | G28: =J8 -> 1340.87 | H28: =E28+F28 -> 275641.25 | I28: =G8 -> 23154.6 | J28: =K8 -> 5306.96 | K28: =I8 -> 3544.6 | L28: =H28/I28 -> 11.904384 | M28: =H28/J28 -> 51.939576 | N28: =E28/K28 -> 77.08689
B29: Varun Beverages | C29: =C9 -> 504.05 | D29: =E29/C29 -> 338.22964 | E29: =D9 -> 170484.65 | F29: =E8 -> 444.16 | G29: =J9 -> 1998.49 | H29: =E29+F29 -> 170928.81 | I29: =G9 -> 22692.63 | J29: =K9 -> 5304.92 | K29: =I9 -> 3209.4 | L29: =H29/I29 -> 7.532349 | M29: =H29/J29 -> 32.220808 | N29: =E29/K29 -> 53.120412
B30: Britannia Inds. | C30: =C10 -> 5115 | D30: =E30/C30 -> 24.086821 | E30: =D10 -> 123204.09 | F30: =E9 -> 2508.18 | G30: =J10 -> 352.44 | H30: =E30+F30 -> 125712.27 | I30: =G10 -> 19151.59 | J30: =K10 -> 3514.34 | K30: =I10 -> 2537.01 | L30: =H30/I30 -> 6.5640644 | M30: =H30/J30 -> 35.771232 | N30: =E30/K30 -> 48.562714
B32: Average | L32: =AVERAGE(L27:L30) -> 7.6487161 | M32: =AVERAGE(M27:M30) -> 33.300185 | N32: =AVERAGE(N27:N30) -> 48.984612
B33: Median | L33: =MEDIAN(L27:L30) -> 7.0482067 | M33: =MEDIAN(M27:M30) -> 33.99602 | N33: =MEDIAN(N27:N30) -> 50.841563
B35: HUL Limited | C35: =C6 -> 2130.15 | D35: =E35/C35 -> 234.95911 | E35: =D6 -> 500498.14 | F35: =E6 -> 1478 | G35: =J6 -> 3248 | H35: =E35+F35 -> 501976.14 | I35: =G6 -> 64468 | J35: =K6 -> 15039 | K35: =I6 -> 15059 | L35: =MEDIAN(L29:L32) -> 7.532349 | M35: =MEDIAN(M29:M32) -> 33.300185 | N35: =MEDIAN(N29:N32) -> 48.984612
B37: Metric | C37: COMPS | D37: EV | E37: Net Debt | F37: Equity Value | G37: Shares | H37: Share Price
B38: EV/Sales | C38: {=TRANSPOSE(L33:N33)} -> 7.0482067 | D38: =H35*C38 -> 3538031.6 | E38: =$F$35 -> 1478 | F38: =D38-E38 -> 3536553.6 | G38: =+$D$35 -> 234.95911 | H38: =F38/G38 -> 15051.784
B39: EV/EBITDA | C39: 33.99602 | D39: =J35*C39 -> 511266.14 | E39: =$F$35 -> 1478 | F39: =D39-E39 -> 509788.14 | G39: =+$D$35 -> 234.95911 | H39: =F39/G39 -> 2169.6888
B40: P/E | C40: 50.841563 | D40: =F40+E40 -> 767101.09 | E40: =$F$35 -> 1478 | F40: =C40*K35 -> 765623.09 | G40: =+$D$35 -> 234.95911 | H40: =F40/G40 -> 3258.5376

Sheet Data Sheet
A1: COMPANY NAME | B1: HINDUSTAN UNILEVER LTD | E1: =IF(B2<>B3, "A NEW VERSION OF THE WORKSHEET IS AVAILABLE", "")
A2: LATEST VERSION | B2: 2.1 | E2: PLEASE DO NOT MAKE ANY CHANGES TO THIS SHEET
A3: CURRENT VERSION | B3: 2.1
A5: META
A6: Number of shares | B6: =IF(B9>0, B9/B8, 0) -> 234.95911
A7: Face Value | B7: 1
A8: Current Price | B8: 2169.7
A9: Market Capitalization | B9: 509790.78
A15: PROFIT & LOSS
A16: Report Date | B16: 42825 | C16: 43190 | D16: 43555 | E16: 43921 | F16: 44286 | G16: 44651 | H16: 45016 | I16: 45382 | J16: 45747 | K16: 46112
A17: Sales | B17: 33162 | C17: 35545 | D17: 39310 | E17: 39783 | F17: 47028 | G17: 52446 | H17: 60580 | I17: 61896 | J17: 61328 | K17: 64468
A18: Raw Material Cost | B18: 13606 | C18: 14233 | D18: 15845 | E18: 15697 | F18: 20141 | G18: 22871 | H18: 28427 | I18: 26822 | J18: 26602 | K18: 29158
A19: Change in Inventory | B19: -144 | C19: 72 | D19: -12 | E19: 108 | F19: 405 | G19: 22 | H19: 75 | I19: 11 | J19: 125 | K19: 429
A20: Power and Fuel | B20: 295 | C20: 295 | D20: 308 | E20: 299 | F20: 339 | G20: 318 | H20: 384 | I20: 446 | J20: 403 | K20: 426
A21: Other Mfr. Exp | B21: 2887 | C21: 2998 | D21: 3041 | E21: 2906 | F21: 2868 | G21: 3354 | H21: 3791 | I21: 3385 | J21: 3687 | K21: 3304
A22: Employee Cost | B22: 1743 | C22: 1860 | D22: 1875 | E22: 1820 | F22: 2358 | G22: 2545 | H22: 2854 | I22: 3009 | J22: 2952 | K22: 3175
A23: Selling and admin | B23: 6689 | C23: 7252 | D23: 7796 | E23: 7620 | F23: 7906 | G23: 8164 | H23: 8785 | I23: 10780 | J23: 10145 | K23: 10744
A24: Other Expenses | B24: 1470 | C24: 1480 | D24: 1553 | E24: 1688 | F24: 2195 | G24: 2359 | H24: 2267 | I24: 2806 | J24: 2966 | K24: 3051
A25: Other Income | B25: 606 | C25: 353 | D25: 322 | E25: 424 | F25: 170 | G25: 219 | H25: 448 | I25: 817 | J25: 1355 | K25: 4923
A26: Depreciation | B26: 432 | C26: 520 | D26: 565 | E26: 1002 | F26: 1074 | G26: 1091 | H26: 1137 | I26: 1216 | J26: 1253 | K26: 1333
A27: Interest | B27: 35 | C27: 26 | D27: 33 | E27: 118 | F27: 117 | G27: 106 | H27: 114 | I27: 334 | J27: 381 | K27: 410
... A31: Dividend Amount | B31: 3672 | C31: 4320 | D31: 4752 | E31: 5400 | F31: 9517.5 | G31: 7990 | H31: 9165 | I31: 9870 | J31: 12455 | K31: 9635
A40: Quarters
A41: Report Date | B41: 45291 | C41: 45382 | D41: 45473 | E41: 45565 | F41: 45657 | G41: 45747 | H41: 45838 | I41: 45930 | J41: 46022 | K41: 46112
A42: Sales | B42: 15567 | C42: 15210 | D42: 15707 | E42: 15926 | F42: 15556 | G42: 15190 | H42: 16514 | I42: 15919 | J42: 16441 | K42: 16351
A43: Expenses | B43: 11902 | C43: 11675 | D43: 11965 | E43: 12139 | F43: 11867 | G43: 11572 | H43: 12797 | I43: 12137 | J43: 12660 | K43: 12514
A44: Other Income | B44: 184 | C44: 309 | D44: 209 | E44: 203 | F44: 733 | G44: 149 | H44: 74 | I44: 269 | J44: 4048 | K44: 503
A45: Depreciation | B45: 313 | C45: 320 | D45: 329 | E45: 338 | F45: 318 | G45: 318 | H45: 361 | I45: 322 | J45: 337 | K45: 348
A46: Interest | B46: 91 | C46: 105 | D46: 93 | E46: 110 | F46: 109 | G46: 77 | H46: 127 | I46: 124 | J46: 88 | K46: 76
A47: Profit before tax | B47: 3445 | C47: 3419 | D47: 3529 | E47: 3542 | F47: 3995 | G47: 3372 | H47: 3303 | I47: 3605 | J47: 7404 | K47: 3916
A48: Tax | B48: 937 | C48: 858 | D48: 917 | E48: 947 | F48: 1006 | G48: 897 | H48: 535 | I48: 911 | J48: 801 | K48: 922
A49: Net profit | B49: 2509 | C49: 2558 | D49: 2610 | E49: 2591 | F49: 2984 | G49: 2464 | H49: 2756 | I49: 2685 | J49: 6607 | K49: 2992
A50: Operating Profit | B50: 3665 | C50: 3535 | D50: 3742 | E50: 3787 | F50: 3689 | G50: 3618 | H50: 3717 | I50: 3782 | J50: 3781 | K50: 3837
A55: BALANCE SHEET
A56: Report Date | B56: 42825 | C56: 43190 | D56: 43555 | E56: 43921 | F56: 44286 | G56: 44651 | H56: 45016 | I56: 45382 | J56: 45747 | K56: 46112
A57: Equity Share Capital | B57: 216 | C57: 216 | D57: 216 | E57: 216 | F57: 235 | G57: 235 | H57: 235 | I57: 235 | J57: 235 | K57: 235
A58: Reserves | B58: 6528 | C58: 7065 | D58: 7651 | E58: 8013 | F58: 47439 | G58: 48826 | H58: 50069 | I58: 50983 | J58: 49167 | K58: 48504
A59: Borrowings | B59: 277 | D59: 99 | G59: 1043 | H59: 1219 | I59: 1484 | J59: 1648 | K59: 1478
A60: Other Liabilities | B60: 8685 | C60: 10581 | D60: 10663 | E60: 11924 | F60: 21066 | G60: 20402 | H60: 21554 | I60: 25787 | J60: 28813 | K60: 29521
A61: Total | B61: 15706 | C61: 17862 | D61: 18629 | E61: 20153 | F61: 68740 | G61: 70506 | H61: 73077 | I61: 78489 | J61: 79863 | K61: 79738
A62: Net Block | B62: 4419 | C62: 4528 | D62: 4715 | E62: 5479 | F62: 51443 | G62: 51473 | H62: 52678 | I62: 53744 | J62: 54335 | K62: 57428
A63: Capital Work in Progress | B63: 229 | C63: 461 | D63: 406 | E63: 597 | F63: 745 | G63: 1313 | H63: 1132 | I63: 1025 | J63: 1009 | K63: 880
A64: Investments | B64: 3794 | C64: 2873 | D64: 2716 | E64: 1255 | F64: 2709 | G64: 3521 | H64: 2882 | I64: 4625 | J64: 3810 | K64: 4359
A65: Other Assets | B65: 7264 | C65: 10000 | D65: 10792 | E65: 12822 | F65: 13843 | G65: 14199 | H65: 16385 | I65: 19095 | J65: 20709 | K65: 17071
A66: Total | B66: 15706 | C66: 17862 | D66: 18629 | E66: 20153 | F66: 68740 | G66: 70506 | H66: 73077 | I66: 78489 | J66: 79863 | K66: 79738
A67: Receivables | B67: 1085 | C67: 1310 | D67: 1816 | E67: 1149 | F67: 1758 | G67: 2236 | H67: 3079 | I67: 2997 | J67: 3819 | K67: 3379
A68: Inventory | B68: 2541 | C68: 2513 | D68: 2574 | E68: 2767 | F68: 3579 | G68: 4096 | H68: 4251 | I68: 4022 | J68: 4415 | K68: 4789
A69: Cash & Bank | B69: 1828 | C69: 3485 | D69: 3757 | E69: 5113 | F69: 4471 | G69: 3846 | H69: 4678 | I69: 7559 | J69: 7554 | K69: 3248
A70: No. of Equity Shares | B70: 2164349639 | C70: 2164528777 | D70: 2164704405 | E70: 2164704405 | F70: 2349567819 | G70: 2349591262 | H70: 2349591262 | I70: 2349591262 | J70: 2349591262 | K70: 2349591262
A71: New Bonus Shares
A72: Face value | B72: 1 | C72: 1 | D72: 1 | E72: 1 | F72: 1 | G72: 1 | H72: 1 | I72: 1 | J72: 1 | K72: 1
A80: CASH FLOW:
A81: Report Date | B81: 42825 | C81: 43190 | D81: 43555 | E81: 43921 | F81: 44286 | G81: 44651 | H81: 45016 | I81: 45382 | J81: 45747 | K81: 46112
A82: Cash from Operating Activity | B82: 5185 | C82: 6059 | D82: 5800 | E82: 7623 | F82: 9163 | G82: 9048 | H82: 9991 | I82: 15469 | J82: 11886 | K82: 10999
A83: Cash from Investing Activity | B83: -1173 | C83: -1063 | D83: -438 | E83: 1791 | F83: -1228 | G83: -1728 | H83: -1484 | I83: -5324 | J83: 6473 | K83: -3676
A84: Cash from Financing Activity | B84: -4214 | C84: -4975 | D84: -5390 | E84: -6819 | F84: -9309 | G84: -8015 | H84: -8953 | I84: -10034 | J84: -13101 | K84: -10810
A85: Net Cash Flow | B85: -202 | C85: 21 | D85: -28 | E85: 2595 | F85: -1374 | G85: -695 | H85: -446 | I85: 111 | J85: 5258 | K85: -3487
A87: Changes in WC | I87: =SUM(H67:H68)-SUM(I67:I68) -> 311 | J87: =SUM(I67:I68)-SUM(J67:J68) -> -1215 | K87: =SUM(J67:J68)-SUM(K67:K68) -> 66
A88: Total Investment | I88: =I87+I83 -> -5013 | J88: =J87+J83 -> 5258 | K88: =K87+K83 -> -3610
A89: NOPAT | I89: ='DCF Model'!E52*(1-Tax_rate) -> 10082.25 | J89: ='DCF Model'!F52*(1-Tax_rate) -> 10083.75 | K89: ='DCF Model'!G52*(1-Tax_rate) -> 10279.5
I90: =I88/I89 -> -0.49721044 | J90: =J88/J89 -> 0.521433 | K90: =K88/K89 -> -0.3511844
A91: PRICE: | B91: 872.61 | C91: 1276.11 | D91: 1633.53 | E91: 2199.83 | F91: 2327.12 | G91: 1960.7 | H91: 2450.44 | I91: 2167.14 | J91: 2161.88 | K91: 2055.2
A93: DERIVED:
A94: Adjusted Equity Shares in Cr | B94: 216.43 | C94: 216.45 | D94: 216.47 | E94: 216.48 | F94: 234.96 | G94: 234.96 | H94: 234.96 | I94: 234.96 | J94: 234.96 | K94: 234.96

Sheet Comps
B1: COMPARABLE COMPANY ANALYSIS
B2: Financial Modelling Course
B6: Comps Data
B8: Company | C8: Ticker | D8: Price | E8: Market Cap | F8: Sales | G8: EBITDA | H8: Net Income | I8: Beta | J8: Total Debt | K8: Cash & Cash Equivalents | L8: EV/EBITDA | M8: P/E
B9: Trent Limited | C9: TRENT | D9: 4791 | E9: 170282 | F9: 17135 | G9: 9270 | H9: 1448 | I9: 0.79 | J9: 2237 | K9: 973 | L9: 110.1 | M9: 102.3
B10: Avenue Supermarts (DMART) | C10: DMART | D10: 4274 | E10: 278260 | F10: 59358 | G10: 22940 | H10: 2707 | I10: 0.63 | J10: 1609 | K10: 210 | L10: 101.3 | M10: 93.4
B11: Vishal Mega Mart | C11: VMM | D11: 148 | E11: 69155 | F11: 10716 | G11: 2730 | H11: 632 | I11: 0.92 | J11: 1093 | K11: 986 | L11: 109.6 | M11: 133.4
B12: Aditya Birla Lifestyle Brands | C12: ABLBL | D12: 139 | E12: 16959 | F12: 7830 | G12: 820 | H12: 59.6 | I12: 0.88 | J12: 512 | K12: 407 | L12: 283.5 | M12: 123
B13: Vedant Fashions (Manyavar) | C13: MANYAVAR | D13: 688 | E13: 16720 | F13: 1386 | G13: 610 | H13: 388 | I13: 0.55 | J13: 483 | K13: 726 | L13: 42.3 | M13: 87.9
B15: Industry Beta
C17: Equity | D17: Total | E17: Debt/ | F17: Debt/ | G17: Tax | H17: Levered | I17: Unlevered
B18: Company Name | C18: Value | D18: Debt | E18: Equity | F18: Capital | G18: Rate % | H18: Beta | I18: Beta
B19: =B10 -> Avenue Supermarts (DMART)
B20: =B11 -> Vishal Mega Mart
B21: =B12 -> Aditya Birla Lifestyle Brands
B22: =B13 -> Vedant Fashions (Manyavar)
B23: Average
B24: Median
B26: Comparable Companies Analysis
D28: Market Data | J28: Financial Data | M28: Valuation
D29: Price | E29: Shares | F29: Market Cap | G29: Debt | H29: Cash | I29: EV | J29: Sales | K29: EBITDA | L29: Earnings | M29: EV/Sales | N29: EV/EBITDA | O29: P/E
B30: Company Name | C30: Ticker | D30: (₹/share) | E30: M | F30: ₹ MM | H30: & Equivalents | I30: ₹ MM | J30: ₹ MM | K30: ₹ MM | L30: ₹ MM | M30: x | N30: x | O30: x
B36: Average
B37: Median
B39: =B9 -> Trent Limited
B41: Metric | C41: Comps | D41: EV | E41: Net Debt | F41: Equity Value | G41: Shares | H41: Share Price
